Metadata-Version: 1.0
Name: GB-dist
Version: 1.0
Summary: Gaussian and Binomial distributions
Home-page: UNKNOWN
Author: Manish kumar thota
Author-email: manish.thota1999@gmail.com
License: UNKNOWN
Platform: UNKNOWN
